eoq3autobahnws/__init__.py
eoq3autobahnws/autobahnwsdomainclient/__init__.py
eoq3autobahnws/autobahnwsdomainclient/autobahnwsdomainclient.py
eoq3autobahnws/autobahnwsdomainhost/__init__.py
eoq3autobahnws/autobahnwsdomainhost/autobahnwsdomainhost.py
eoq3autobahnws/util/__init__.py
eoq3autobahnws/util/interproc.py
eoq3autobahnws/util/ssl.py
eoq3autobahnws-2.9.4.dist-info/LICENSE
eoq3autobahnws-2.9.4.dist-info/METADATA
eoq3autobahnws-2.9.4.dist-info/WHEEL
eoq3autobahnws-2.9.4.dist-info/top_level.txt
eoq3autobahnws-2.9.4.dist-info/RECORD
