Metadata-Version: 2.2
Name: eoq3autobahnws
Version: 2.9.4
Summary: Websocket domain client and host using autobahn
Author-email: Bjoern Annighoefer <bjoern.annighoefer@ils.uni-stuttgart.de>
Project-URL: Homepage, https://gitlab.com/eoq/py/eoq3autobahnws
Project-URL: Issues, https://gitlab.com/eoq/py/eoq3autobahnws/-/issues
Classifier: Programming Language :: Python :: 3
Classifier: License :: OSI Approved :: MIT License
Classifier: Operating System :: OS Independent
Requires-Python: >=3.10
License-File: LICENSE
Requires-Dist: eoq3
Requires-Dist: autobahn
